[
    {
        "name": "Md. Ferdus Tuser",
        "comment": "Best product seller, I get one from them and the post service of time keeper is awesome",
        "rating": 5
    },
    {
        "name": "Umar Faruk Hridoy",
        "comment": "Best product seller, I get one from them and the post service of time keeper is awesome",
        "rating": 5
    },
    {
        "name": "Fakhruddin Ahmed Mia",
        "comment": "Best product seller, I get one from them and the post service of time keeper is awesome",
        "rating": 5
    }
]